MANIFEST.in
README.md
setup.py
card_me/__init__.py
card_me/base.py
card_me/behavior.py
card_me/change_tz.py
card_me/hcalendar.py
card_me/icalendar.py
card_me/ics_diff.py
card_me/vcard.py
card_me/win32tz.py
python_card_me.egg-info/PKG-INFO
python_card_me.egg-info/SOURCES.txt
python_card_me.egg-info/dependency_links.txt
python_card_me.egg-info/entry_points.txt
python_card_me.egg-info/requires.txt
python_card_me.egg-info/top_level.txt
python_card_me.egg-info/zip-safe
test_files/availablity.ics
test_files/badline.ics
test_files/badstream.ics
test_files/freebusy.ics
test_files/journal.ics
test_files/ms_tzid.ics
test_files/recurrence.ics
test_files/ruby_rrule.ics
test_files/silly_test.ics
test_files/simple_2_0_test.ics
test_files/simple_3_0_test.ics
test_files/simple_test.ics
test_files/standard_test.ics
test_files/timezones.ics
test_files/tzid_8bit.ics
test_files/utf8_test.ics
test_files/vcard_with_groups.ics
test_files/vtodo.ics