Metadata-Version: 1.1
Name: python-card-me
Version: 0.9.1
Summary: UNKNOWN
Home-page: https://github.com/tBaxter/python-card-me
Author: Tim Baxter, Jeffrey Harris
Author-email: mail.baxter@gmail.com
License: Apache
Platform: any
Classifier: Development Status :: 5 - Production/Stable
Classifier:           Environment :: Console
Classifier:           License :: OSI Approved :: BSD License
Classifier:           Intended Audience :: Developers
Classifier:           Natural Language :: English
Classifier:           Programming Language :: Python
Classifier:           Operating System :: OS Independent
Classifier:           Topic :: Text Processing
